alien/__init__.py
alien/alien.py
alien/comments.py
alien/submissions.py
alien/utils.py
alien-0.0.8b0.dist-info/LICENSE
alien-0.0.8b0.dist-info/METADATA
alien-0.0.8b0.dist-info/WHEEL
alien-0.0.8b0.dist-info/top_level.txt
alien-0.0.8b0.dist-info/RECORD
